{
  "date": "2026-06-24",
  "prev_date": "2026-06-23",
  "periods": {
    "7": {
      "period": "近 7 日",
      "source": "rule",
      "summary": "近 7 日里，幻想言情、古风言情 是更热的综合赛道，具体分类以 古风世情、快穿、女频悬疑 的榜单动能更强；题材上 系统、重生、女配、空间、双洁、反派 反复出现，说明读者仍偏好强设定、强情绪钩子和明确爽点。",
      "fallback_summary": "近 7 日里，幻想言情、古风言情 是更热的综合赛道，具体分类以 古风世情、快穿、女频悬疑 的榜单动能更强；题材上 系统、重生、女配、空间、双洁、反派 反复出现，说明读者仍偏好强设定、强情绪钩子和明确爽点。",
      "hot_genres": [
        {
          "name": "幻想言情",
          "score": 714,
          "new_count": 42,
          "dropped_count": 42,
          "read_count": 84,
          "active_days": 28,
          "lead_category": "女频悬疑",
          "categories": [
            "玄幻言情",
            "科幻末世",
            "悬疑脑洞",
            "女频悬疑"
          ]
        },
        {
          "name": "古风言情",
          "score": 712,
          "new_count": 42,
          "dropped_count": 42,
          "read_count": 84,
          "active_days": 28,
          "lead_category": "古风世情",
          "categories": [
            "古风世情",
            "古言脑洞",
            "宫斗宅斗",
            "种田"
          ]
        },
        {
          "name": "现代言情",
          "score": 662,
          "new_count": 34,
          "dropped_count": 34,
          "read_count": 84,
          "active_days": 28,
          "lead_category": "现言脑洞",
          "categories": [
            "现言脑洞",
            "豪门总裁",
            "职场婚恋",
            "青春甜宠"
          ]
        },
        {
          "name": "快穿衍生",
          "score": 376,
          "new_count": 24,
          "dropped_count": 24,
          "read_count": 42,
          "active_days": 14,
          "lead_category": "快穿",
          "categories": [
            "快穿",
            "女频衍生"
          ]
        },
        {
          "name": "年代民国",
          "score": 362,
          "new_count": 22,
          "dropped_count": 22,
          "read_count": 42,
          "active_days": 14,
          "lead_category": "年代",
          "categories": [
            "年代",
            "民国言情"
          ]
        }
      ],
      "hot_types": [
        {
          "name": "古风世情",
          "score": 194,
          "new_count": 13,
          "dropped_count": 13,
          "read_count": 21,
          "active_days": 7
        },
        {
          "name": "快穿",
          "score": 194,
          "new_count": 13,
          "dropped_count": 13,
          "read_count": 21,
          "active_days": 7
        },
        {
          "name": "女频悬疑",
          "score": 194,
          "new_count": 13,
          "dropped_count": 13,
          "read_count": 21,
          "active_days": 7
        },
        {
          "name": "年代",
          "score": 188,
          "new_count": 12,
          "dropped_count": 12,
          "read_count": 21,
          "active_days": 7
        },
        {
          "name": "女频衍生",
          "score": 182,
          "new_count": 11,
          "dropped_count": 11,
          "read_count": 21,
          "active_days": 7
        },
        {
          "name": "古言脑洞",
          "score": 178,
          "new_count": 11,
          "dropped_count": 11,
          "read_count": 21,
          "active_days": 7
        }
      ],
      "hot_themes": [
        {
          "name": "系统",
          "count": 156,
          "category_count": 17
        },
        {
          "name": "重生",
          "count": 117,
          "category_count": 18
        },
        {
          "name": "女配",
          "count": 78,
          "category_count": 13
        },
        {
          "name": "空间",
          "count": 73,
          "category_count": 12
        },
        {
          "name": "双洁",
          "count": 68,
          "category_count": 13
        },
        {
          "name": "反派",
          "count": 64,
          "category_count": 14
        },
        {
          "name": "团宠",
          "count": 59,
          "category_count": 14
        },
        {
          "name": "末世",
          "count": 56,
          "category_count": 4
        },
        {
          "name": "快穿",
          "count": 54,
          "category_count": 3
        },
        {
          "name": "年代",
          "count": 52,
          "category_count": 5
        },
        {
          "name": "穿书",
          "count": 45,
          "category_count": 12
        },
        {
          "name": "炮灰",
          "count": 44,
          "category_count": 10
        },
        {
          "name": "甜宠",
          "count": 43,
          "category_count": 14
        },
        {
          "name": "强制爱",
          "count": 36,
          "category_count": 9
        }
      ]
    },
    "14": {
      "period": "近 14 日",
      "source": "rule",
      "summary": "近 14 日里，古风言情、幻想言情 是更热的综合赛道，具体分类以 快穿、年代、古风世情 的榜单动能更强；题材上 系统、重生、团宠、女配、空间、反派 反复出现，说明读者仍偏好强设定、强情绪钩子和明确爽点。",
      "fallback_summary": "近 14 日里，古风言情、幻想言情 是更热的综合赛道，具体分类以 快穿、年代、古风世情 的榜单动能更强；题材上 系统、重生、团宠、女配、空间、反派 反复出现，说明读者仍偏好强设定、强情绪钩子和明确爽点。",
      "hot_genres": [
        {
          "name": "古风言情",
          "score": 1446,
          "new_count": 88,
          "dropped_count": 88,
          "read_count": 168,
          "active_days": 56,
          "lead_category": "古风世情",
          "categories": [
            "古风世情",
            "古言脑洞",
            "宫斗宅斗",
            "种田"
          ]
        },
        {
          "name": "幻想言情",
          "score": 1394,
          "new_count": 81,
          "dropped_count": 81,
          "read_count": 168,
          "active_days": 56,
          "lead_category": "科幻末世",
          "categories": [
            "玄幻言情",
            "科幻末世",
            "悬疑脑洞",
            "女频悬疑"
          ]
        },
        {
          "name": "现代言情",
          "score": 1390,
          "new_count": 79,
          "dropped_count": 79,
          "read_count": 168,
          "active_days": 56,
          "lead_category": "职场婚恋",
          "categories": [
            "现言脑洞",
            "豪门总裁",
            "职场婚恋",
            "青春甜宠"
          ]
        },
        {
          "name": "快穿衍生",
          "score": 738,
          "new_count": 46,
          "dropped_count": 46,
          "read_count": 84,
          "active_days": 28,
          "lead_category": "快穿",
          "categories": [
            "快穿",
            "女频衍生"
          ]
        },
        {
          "name": "年代民国",
          "score": 698,
          "new_count": 40,
          "dropped_count": 40,
          "read_count": 84,
          "active_days": 28,
          "lead_category": "年代",
          "categories": [
            "年代",
            "民国言情"
          ]
        }
      ],
      "hot_types": [
        {
          "name": "快穿",
          "score": 387,
          "new_count": 26,
          "dropped_count": 26,
          "read_count": 42,
          "active_days": 14
        },
        {
          "name": "年代",
          "score": 385,
          "new_count": 26,
          "dropped_count": 26,
          "read_count": 42,
          "active_days": 14
        },
        {
          "name": "古风世情",
          "score": 369,
          "new_count": 23,
          "dropped_count": 23,
          "read_count": 42,
          "active_days": 14
        },
        {
          "name": "职场婚恋",
          "score": 369,
          "new_count": 24,
          "dropped_count": 24,
          "read_count": 42,
          "active_days": 14
        },
        {
          "name": "现言脑洞",
          "score": 363,
          "new_count": 22,
          "dropped_count": 22,
          "read_count": 42,
          "active_days": 14
        },
        {
          "name": "宫斗宅斗",
          "score": 363,
          "new_count": 22,
          "dropped_count": 22,
          "read_count": 42,
          "active_days": 14
        }
      ],
      "hot_themes": [
        {
          "name": "系统",
          "count": 230,
          "category_count": 18
        },
        {
          "name": "重生",
          "count": 177,
          "category_count": 18
        },
        {
          "name": "团宠",
          "count": 132,
          "category_count": 16
        },
        {
          "name": "女配",
          "count": 119,
          "category_count": 13
        },
        {
          "name": "空间",
          "count": 118,
          "category_count": 13
        },
        {
          "name": "反派",
          "count": 110,
          "category_count": 15
        },
        {
          "name": "甜宠",
          "count": 100,
          "category_count": 17
        },
        {
          "name": "双洁",
          "count": 88,
          "category_count": 13
        },
        {
          "name": "快穿",
          "count": 82,
          "category_count": 4
        },
        {
          "name": "无CP",
          "count": 80,
          "category_count": 15
        },
        {
          "name": "末世",
          "count": 79,
          "category_count": 4
        },
        {
          "name": "强制爱",
          "count": 76,
          "category_count": 9
        },
        {
          "name": "穿书",
          "count": 75,
          "category_count": 13
        },
        {
          "name": "炮灰",
          "count": 66,
          "category_count": 11
        }
      ]
    },
    "30": {
      "period": "近 30 日",
      "source": "rule",
      "summary": "近 30 日里，古风言情、现代言情 是更热的综合赛道，具体分类以 宫斗宅斗、年代、女频衍生 的榜单动能更强；题材上 系统、重生、团宠、甜宠、无CP、女配 反复出现，说明读者仍偏好强设定、强情绪钩子和明确爽点。",
      "fallback_summary": "近 30 日里，古风言情、现代言情 是更热的综合赛道，具体分类以 宫斗宅斗、年代、女频衍生 的榜单动能更强；题材上 系统、重生、团宠、甜宠、无CP、女配 反复出现，说明读者仍偏好强设定、强情绪钩子和明确爽点。",
      "hot_genres": [
        {
          "name": "古风言情",
          "score": 3046,
          "new_count": 181,
          "dropped_count": 181,
          "read_count": 360,
          "active_days": 120,
          "lead_category": "宫斗宅斗",
          "categories": [
            "古风世情",
            "古言脑洞",
            "宫斗宅斗",
            "种田"
          ]
        },
        {
          "name": "现代言情",
          "score": 2944,
          "new_count": 164,
          "dropped_count": 164,
          "read_count": 360,
          "active_days": 120,
          "lead_category": "现言脑洞",
          "categories": [
            "现言脑洞",
            "豪门总裁",
            "职场婚恋",
            "青春甜宠"
          ]
        },
        {
          "name": "幻想言情",
          "score": 2894,
          "new_count": 157,
          "dropped_count": 157,
          "read_count": 360,
          "active_days": 120,
          "lead_category": "玄幻言情",
          "categories": [
            "玄幻言情",
            "科幻末世",
            "悬疑脑洞",
            "女频悬疑"
          ]
        },
        {
          "name": "快穿衍生",
          "score": 1546,
          "new_count": 93,
          "dropped_count": 93,
          "read_count": 180,
          "active_days": 60,
          "lead_category": "女频衍生",
          "categories": [
            "快穿",
            "女频衍生"
          ]
        },
        {
          "name": "年代民国",
          "score": 1468,
          "new_count": 83,
          "dropped_count": 83,
          "read_count": 180,
          "active_days": 60,
          "lead_category": "年代",
          "categories": [
            "年代",
            "民国言情"
          ]
        }
      ],
      "hot_types": [
        {
          "name": "宫斗宅斗",
          "score": 811,
          "new_count": 53,
          "dropped_count": 53,
          "read_count": 90,
          "active_days": 30
        },
        {
          "name": "年代",
          "score": 785,
          "new_count": 49,
          "dropped_count": 49,
          "read_count": 90,
          "active_days": 30
        },
        {
          "name": "女频衍生",
          "score": 777,
          "new_count": 47,
          "dropped_count": 47,
          "read_count": 90,
          "active_days": 30
        },
        {
          "name": "快穿",
          "score": 769,
          "new_count": 46,
          "dropped_count": 46,
          "read_count": 90,
          "active_days": 30
        },
        {
          "name": "种田",
          "score": 763,
          "new_count": 46,
          "dropped_count": 46,
          "read_count": 90,
          "active_days": 30
        },
        {
          "name": "现言脑洞",
          "score": 761,
          "new_count": 45,
          "dropped_count": 45,
          "read_count": 90,
          "active_days": 30
        }
      ],
      "hot_themes": [
        {
          "name": "系统",
          "count": 411,
          "category_count": 18
        },
        {
          "name": "重生",
          "count": 288,
          "category_count": 18
        },
        {
          "name": "团宠",
          "count": 267,
          "category_count": 16
        },
        {
          "name": "甜宠",
          "count": 227,
          "category_count": 18
        },
        {
          "name": "无CP",
          "count": 204,
          "category_count": 18
        },
        {
          "name": "女配",
          "count": 189,
          "category_count": 14
        },
        {
          "name": "空间",
          "count": 162,
          "category_count": 13
        },
        {
          "name": "反派",
          "count": 161,
          "category_count": 16
        },
        {
          "name": "穿书",
          "count": 158,
          "category_count": 16
        },
        {
          "name": "强制爱",
          "count": 154,
          "category_count": 12
        },
        {
          "name": "快穿",
          "count": 151,
          "category_count": 6
        },
        {
          "name": "双洁",
          "count": 133,
          "category_count": 13
        },
        {
          "name": "末世",
          "count": 124,
          "category_count": 5
        },
        {
          "name": "炮灰",
          "count": 117,
          "category_count": 13
        }
      ]
    },
    "all": {
      "period": "全部样本",
      "source": "rule",
      "summary": "全部样本里，古风言情、现代言情 是更热的综合赛道，具体分类以 宫斗宅斗、年代、女频衍生 的榜单动能更强；题材上 系统、重生、女配、团宠、穿书、甜宠 反复出现，说明读者仍偏好强设定、强情绪钩子和明确爽点。",
      "fallback_summary": "全部样本里，古风言情、现代言情 是更热的综合赛道，具体分类以 宫斗宅斗、年代、女频衍生 的榜单动能更强；题材上 系统、重生、女配、团宠、穿书、甜宠 反复出现，说明读者仍偏好强设定、强情绪钩子和明确爽点。",
      "hot_genres": [
        {
          "name": "古风言情",
          "score": 7588,
          "new_count": 459,
          "dropped_count": 459,
          "read_count": 888,
          "active_days": 296,
          "lead_category": "宫斗宅斗",
          "categories": [
            "古风世情",
            "古言脑洞",
            "宫斗宅斗",
            "种田"
          ]
        },
        {
          "name": "现代言情",
          "score": 7348,
          "new_count": 418,
          "dropped_count": 418,
          "read_count": 888,
          "active_days": 296,
          "lead_category": "职场婚恋",
          "categories": [
            "现言脑洞",
            "豪门总裁",
            "职场婚恋",
            "青春甜宠"
          ]
        },
        {
          "name": "幻想言情",
          "score": 7136,
          "new_count": 388,
          "dropped_count": 388,
          "read_count": 888,
          "active_days": 296,
          "lead_category": "科幻末世",
          "categories": [
            "玄幻言情",
            "科幻末世",
            "悬疑脑洞",
            "女频悬疑"
          ]
        },
        {
          "name": "快穿衍生",
          "score": 3866,
          "new_count": 239,
          "dropped_count": 239,
          "read_count": 444,
          "active_days": 148,
          "lead_category": "快穿",
          "categories": [
            "快穿",
            "女频衍生"
          ]
        },
        {
          "name": "年代民国",
          "score": 3584,
          "new_count": 197,
          "dropped_count": 197,
          "read_count": 444,
          "active_days": 148,
          "lead_category": "年代",
          "categories": [
            "年代",
            "民国言情"
          ]
        }
      ],
      "hot_types": [
        {
          "name": "宫斗宅斗",
          "score": 2019,
          "new_count": 134,
          "dropped_count": 134,
          "read_count": 222,
          "active_days": 74
        },
        {
          "name": "年代",
          "score": 1943,
          "new_count": 122,
          "dropped_count": 122,
          "read_count": 222,
          "active_days": 74
        },
        {
          "name": "女频衍生",
          "score": 1933,
          "new_count": 119,
          "dropped_count": 119,
          "read_count": 222,
          "active_days": 74
        },
        {
          "name": "快穿",
          "score": 1933,
          "new_count": 120,
          "dropped_count": 120,
          "read_count": 222,
          "active_days": 74
        },
        {
          "name": "职场婚恋",
          "score": 1893,
          "new_count": 115,
          "dropped_count": 115,
          "read_count": 222,
          "active_days": 74
        },
        {
          "name": "古风世情",
          "score": 1881,
          "new_count": 111,
          "dropped_count": 111,
          "read_count": 222,
          "active_days": 74
        }
      ],
      "hot_themes": [
        {
          "name": "系统",
          "count": 759,
          "category_count": 18
        },
        {
          "name": "重生",
          "count": 610,
          "category_count": 18
        },
        {
          "name": "女配",
          "count": 479,
          "category_count": 16
        },
        {
          "name": "团宠",
          "count": 456,
          "category_count": 16
        },
        {
          "name": "穿书",
          "count": 417,
          "category_count": 17
        },
        {
          "name": "甜宠",
          "count": 401,
          "category_count": 18
        },
        {
          "name": "无CP",
          "count": 368,
          "category_count": 18
        },
        {
          "name": "快穿",
          "count": 363,
          "category_count": 9
        },
        {
          "name": "反派",
          "count": 317,
          "category_count": 18
        },
        {
          "name": "空间",
          "count": 312,
          "category_count": 17
        },
        {
          "name": "炮灰",
          "count": 285,
          "category_count": 15
        },
        {
          "name": "强制爱",
          "count": 283,
          "category_count": 14
        },
        {
          "name": "末世",
          "count": 259,
          "category_count": 10
        },
        {
          "name": "追妻",
          "count": 204,
          "category_count": 15
        }
      ]
    }
  }
}